mugatu/__init__.py
mugatu/comm_designs.py
mugatu/designmode.py
mugatu/designs_to_targetdb.py
mugatu/etc/mugatu.yml
mugatu/exceptions.py
mugatu/fpsdesign.py
mugatu/templates/dmode_check_w_dists.html
mugatu/templates/dmode_check_w_dists_sky.html
mugatu/templates/main_validation_page.html
mugatu/templates/valid_check.html
mugatu/templates/valid_check_w_dists.html
sdss_mugatu-2.6.0.dist-info/LICENSE.md
sdss_mugatu-2.6.0.dist-info/METADATA
sdss_mugatu-2.6.0.dist-info/WHEEL
sdss_mugatu-2.6.0.dist-info/RECORD
