Metadata-Version: 2.1
Name: sdss-mugatu
Version: 2.6.0
Summary: Package to read, write and validate FPS designs
Home-page: https://pypi.org/project/sdss-mugatu/
License: BSD 3-Clause License
Author: Ilija Medan
Requires-Python: >=3.9,<4.0
Classifier: License :: Other/Proprietary License
Classifier: Programming Language :: Python :: 3
Classifier: Programming Language :: Python :: 3.9
Classifier: Programming Language :: Python :: 3.10
Classifier: Programming Language :: Python :: 3.11
Classifier: Programming Language :: Python :: 3.12
Requires-Dist: DateTime (>=4.3,<5.0)
Requires-Dist: astropy (>=5.3.3,<6.0.0)
Requires-Dist: fitsio (>=1.0.5,<2.0.0)
Requires-Dist: jupyter (>=1.0.0,<2.0.0)
Requires-Dist: notebook (>=6.4.12,<7.0.0)
Requires-Dist: numpy (>=1.19.5,<2.0.0)
Requires-Dist: ortools (>=9.1.9490,<10.0.0)
Requires-Dist: scipy (>=1.6.0,<2.0.0)
Requires-Dist: sdss-access (==1.1.1)
Requires-Dist: sdss-coordio (>=1.16.0,<2.0.0)
Requires-Dist: sdss-kaiju (==1.3.1)
Requires-Dist: sdssdb (>=0.13.3,<0.14.0)
Project-URL: Documentation, https://mugatu.readthedocs.io/en/latest/
Project-URL: Repository, https://github.com/sdss/mugatu
